README.md
setup.py
channeling/__init__.py
channeling/__main__.py
channeling/batteries.py
channeling/cmd_joke.py
channeling/commands.py
channeling/config.py
channeling/database.py
channeling/message_formatting.py
channeling/tools.py
channeling.egg-info/PKG-INFO
channeling.egg-info/SOURCES.txt
channeling.egg-info/dependency_links.txt
channeling.egg-info/entry_points.txt
channeling.egg-info/requires.txt
channeling.egg-info/top_level.txt