Metadata-Version: 2.1
Name: channeling
Version: 0.0.13
Summary: Channeling - a Discord bot.
Home-page: https://gitlab.com/nul.one/channeling
Author: Predrag Mandic
Author-email: predrag@nul.one
License: BSD
Download-URL: https://gitlab.com/nul.one/channeling/-/archive/0.0.13/channeling-0.0.13.tar.gz
Platform: UNKNOWN
Classifier: Development Status :: 3 - Alpha
Classifier: Environment :: Console
Classifier: Intended Audience :: Developers
Classifier: Intended Audience :: Information Technology
Classifier: Intended Audience :: System Administrators
Classifier: Intended Audience :: Telecommunications Industry
Classifier: License :: OSI Approved :: BSD License
Classifier: Natural Language :: English
Classifier: Operating System :: POSIX :: Linux
Classifier: Programming Language :: Python :: 3 :: Only
Classifier: Natural Language :: English
Classifier: Topic :: Communications :: Chat
Classifier: Topic :: Games/Entertainment
Requires-Python: >=3.6.5
